LICENSE
README.md
setup.py
pynoco/__about__.py
pynoco/__init__.py
pynoco/api.py
pynoco/base.py
pynoco/client.py
pynoco/source.py
pynoco.egg-info/PKG-INFO
pynoco.egg-info/SOURCES.txt
pynoco.egg-info/dependency_links.txt
pynoco.egg-info/requires.txt
pynoco.egg-info/top_level.txt