Metadata-Version: 2.1
Name: pynoco
Version: 1.0.0
Summary: A Python client for NocoDB, The Open Source Airtable Alternative.
Home-page: https://github.com/TalaatHasanin/nocodb-python-client
Author: Talaat Hasanin
Author-email: talaat049@gmail.com
Classifier: Programming Language :: Python :: 3
Classifier: Operating System :: OS Independent
Requires-Python: >=3.8
License-File: LICENSE
